social.eusign-0.1-py2.7-nspkg.pth
social/eusign/__init__.py
social.eusign-0.1.dist-info/DESCRIPTION.rst
social.eusign-0.1.dist-info/METADATA
social.eusign-0.1.dist-info/namespace_packages.txt
social.eusign-0.1.dist-info/pydist.json
social.eusign-0.1.dist-info/RECORD
social.eusign-0.1.dist-info/top_level.txt
social.eusign-0.1.dist-info/WHEEL
