Metadata-Version: 2.0
Name: social.eusign
Version: 0.1
Summary: python-social-auth plugin for EUSign.org
Home-page: https://github.com/dstucrypt/social.eusign
Author: Ilya Petrov, Mikhail Kashkin
Author-email: mkashkin@gmail.com
License: BSD
Platform: UNKNOWN
Classifier: Topic :: Internet
Classifier: License :: OSI Approved :: BSD License
Classifier: Environment :: Web Environment
Classifier: Intended Audience :: Developers
Classifier: Operating System :: OS Independent
Classifier: Programming Language :: Python
Requires-Dist: requests
